pyqsl/__init__.py
pyqsl/common.py
pyqsl/core.py
pyqsl/relation.py
pyqsl/settings.py
pyqsl/simulation_result.py
pyqsl-0.0.0.dist-info/LICENSE
pyqsl-0.0.0.dist-info/METADATA
pyqsl-0.0.0.dist-info/WHEEL
pyqsl-0.0.0.dist-info/top_level.txt
pyqsl-0.0.0.dist-info/RECORD
