Metadata-Version: 2.1
Name: pyqsl
Version: 0.0.0
Summary: A Framework for parametrized sweeps aimed for quantum simulations.
Author: Antti Vepsäläinen
License: The MIT License
Project-URL: url, https://github.com/ittnas/pyqsl
Project-URL: download_url, https://github.com/ittnas/pyqsl/archive/2.0.tar.gz
Classifier: Programming Language :: Python :: 3
Requires-Python: >=3.10
License-File: LICENSE
Requires-Dist: numpy
Requires-Dist: scipy
Requires-Dist: matplotlib
Requires-Dist: tqdm
Requires-Dist: numexpr
Requires-Dist: networkx
Requires-Dist: xarray
Requires-Dist: psutil
Requires-Dist: pint
Requires-Dist: pint-xarray
Provides-Extra: examples
Requires-Dist: qutip (>4.0) ; extra == 'examples'
Provides-Extra: testing
Requires-Dist: pytest ; extra == 'testing'
Requires-Dist: tox ; extra == 'testing'
Requires-Dist: black ; extra == 'testing'
Requires-Dist: isort ; extra == 'testing'
Requires-Dist: sphinx ; extra == 'testing'
